{
  "spelldata": {
    "spells": [
      {
        "id": 0,
        "keyid": "UUU",
        "name": "Earthy Smash",
        "desc": "Fires a simple bolt of rock forward.",
        "damage": 2,
        "speed": 3,
        "cost": 5,
        "distance" : 100,
        "spritepath": "assets/elements/projectiles/0.png"
      },
      {
        "id": 1,
        "keyid": "UUI",
        "name": "",
        "desc": "",
        "damage": null,
        "speed": null,
        "cost": null,
        "spritepath": "assets/elements/projectiles/1.png"
      },
      {
        "id": 2,
        "keyid": "UUO",
        "name": "",
        "desc": "",
        "damage": null,
        "speed": null,
        "cost": null,
        "spritepath": "assets/elements/projectiles/2.png"
      },
      {
        "id": 3,
        "keyid": "UUP",
        "name": "",
        "desc": "",
        "damage": null,
        "speed": null,
        "cost": null,
        "spritepath": "assets/elements/projectiles/3.png"
      },
      {
        "id": 4,
        "keyid": "UII",
        "name": "",
        "desc": "",
        "damage": null,
        "speed": null,
        "cost": null,
        "spritepath": "assets/elements/projectiles/4.png"
      },
      {
        "id": 5,
        "keyid": "UIO",
        "name": "",
        "desc": "",
        "damage": null,
        "speed": null,
        "cost": null,
        "spritepath": "assets/elements/projectiles/5.png"
      },
      {
        "id": 6,
        "keyid": "UIP",
        "name": "",
        "desc": "",
        "damage": null,
        "speed": null,
        "cost": null,
        "spritepath": "assets/elements/projectiles/6.png"
      },
      {
        "id": 7,
        "keyid": "UOO",
        "name": "",
        "desc": "",
        "damage": null,
        "speed": null,
        "cost": null,
        "spritepath": "assets/elements/projectiles/7.png"
      },
      {
        "id": 8,
        "keyid": "UOP",
        "name": "",
        "desc": "",
        "damage": null,
        "speed": null,
        "cost": null,
        "spritepath": "assets/elements/projectiles/8.png"
      },
      {
        "id": 9,
        "keyid": "UPP",
        "name": "",
        "desc": "",
        "damage": null,
        "speed": null,
        "cost": null,
        "spritepath": "assets/elements/projectiles/9.png"
      },
      {
        "id": 10,
        "keyid": "III",
        "name": "Fire Ball",
        "desc": "Fires a simple ball of fire forward.",
        "damage": 1,
        "speed": 11,
        "cost": 5,
        "distance" : 250,
        "spritepath": "assets/elements/projectiles/10.png"
      },
      {
        "id": 11,
        "keyid": "IIO",
        "name": "",
        "desc": "",
        "damage": null,
        "speed": null,
        "cost": null,
        "spritepath": "assets/elements/projectiles/11.png"
      },
      {
        "id": 12,
        "keyid": "IIP",
        "name": "",
        "desc": "",
        "damage": null,
        "speed": null,
        "cost": null,
        "spritepath": "assets/elements/projectiles/12.png"
      },
      {
        "id": 13,
        "keyid": "IOO",
        "name": "",
        "desc": "",
        "damage": null,
        "speed": null,
        "cost": null,
        "spritepath": "assets/elements/projectiles/13.png"
      },
      {
        "id": 14,
        "keyid": "IOP",
        "name": "",
        "desc": "",
        "damage": null,
        "speed": null,
        "cost": null,
        "spritepath": "assets/elements/projectiles/14.png"
      },
      {
        "id": 15,
        "keyid": "IPP",
        "name": "",
        "desc": "",
        "damage": null,
        "speed": null,
        "cost": null,
        "spritepath": "assets/elements/projectiles/15.png"
      },
      {
        "id": 16,
        "keyid": "OOO",
        "name": "Air Slice",
        "desc": "Fires a fast bolt of wind forward.",
        "damage": .5,
        "speed": 15,
        "cost": 5,
        "distance" : 300,
        "spritepath": "assets/elements/projectiles/16.png"
      },
      {
        "id": 17,
        "keyid": "OOP",
        "name": "",
        "desc": "",
        "damage": null,
        "speed": null,
        "cost": null,
        "spritepath": "assets/elements/projectiles/17.png"
      },
      {
        "id": 18,
        "keyid": "OPP",
        "name": "",
        "desc": "",
        "damage": null,
        "speed": null,
        "cost": null,
        "spritepath": "assets/elements/projectiles/18.png"
      },
      {
        "id": 19,
        "keyid": "PPP",
        "name": "Water Whip",
        "desc": "Fires a simple bolt of water forward.",
        "damage": 1.5,
        "speed": 7,
        "cost": 5,
        "distance" : 300,
        "spritepath": "assets/elements/projectiles/19.png"
      }
    ]
  }
}
